Metadata-Version: 1.0
Name: weeblife
Version: 0.1.0
Summary: Random wallpapers and loading animations.
Home-page: https://github.com/JohnDoee/weeblife
Author: Anders Jensen
Author-email: johndoee@tidalstream.org
License: MIT
Platform: UNKNOWN
